pytlu/ZestSC1.py
pytlu/ZestSC1TL.py
pytlu/__init__.py
pytlu/fifo_readout.py
pytlu/stream_fifo.py
pytlu/tlu.py
pytlu/tlu.yaml
pytlu/tlu_eudaq.py
pytlu/tlu_master.py
pytlu/firmware/tlu.bit
pytlu/online_monitor/__init__.py
pytlu/online_monitor/pytlu_converter.py
pytlu/online_monitor/pytlu_producer_sim.py
pytlu/online_monitor/pytlu_receiver.py
pytlu/online_monitor/pytlu_sender.py
pytlu/online_monitor/start_pytlu_online_monitor.py
pytlu-1.0.0.dist-info/LICENSE
pytlu-1.0.0.dist-info/METADATA
pytlu-1.0.0.dist-info/WHEEL
pytlu-1.0.0.dist-info/entry_points.txt
pytlu-1.0.0.dist-info/top_level.txt
pytlu-1.0.0.dist-info/RECORD
